README.md
setup.py
certbot_dns_valuedomain/__init__.py
certbot_dns_valuedomain.egg-info/PKG-INFO
certbot_dns_valuedomain.egg-info/SOURCES.txt
certbot_dns_valuedomain.egg-info/dependency_links.txt
certbot_dns_valuedomain.egg-info/entry_points.txt
certbot_dns_valuedomain.egg-info/requires.txt
certbot_dns_valuedomain.egg-info/top_level.txt